pyraisdk/__init__.py
pyraisdk/dynbatch/__init__.py
pyraisdk/dynbatch/base.py
pyraisdk/dynbatch/batch.py
pyraisdk/dynbatch/config.py
pyraisdk/dynconfig/__init__.py
pyraisdk/dynconfig/common.py
pyraisdk/dynconfig/core.py
pyraisdk/dynconfig/monitor.py
pyraisdk/dynconfig/proxy.py
pyraisdk/dynconfig/shim.py
pyraisdk/dynconfig/utils.py
pyraisdk/otel/__init__.py
pyraisdk/otel/auth.py
pyraisdk/otel/config.py
pyraisdk/otel/customExporter.py
pyraisdk/rlog/__init__.py
pyraisdk/rlog/eventhub.py
pyraisdk/rlog/gputil.py
pyraisdk/rlog/log.py
pyraisdk/rlog/logimp.py
pyraisdk/rlog/reporter.py
pyraisdk/telemetry/__init__.py
pyraisdk/telemetry/logging/__init__.py
pyraisdk/telemetry/logging/exporters/__init__.py
pyraisdk/telemetry/logging/exporters/console.py
pyraisdk/telemetry/logging/exporters/fluent.py
pyraisdk/telemetry/logging/exporters/formatter.py
pyraisdk/telemetry/logging/exporters/singularity.py
pyraisdk/telemetry/logging/flask.py
pyraisdk/telemetry/logging/handler.py
pyraisdk/telemetry/logging/log.py
pyraisdk/telemetry/logging/log_environment.py
pyraisdk/telemetry/logging/provider.py
pyraisdk/telemetry/logging/record.py
pyraisdk/telemetry/logging/utils.py
pyraisdk-0.5.6.dist-info/METADATA
pyraisdk-0.5.6.dist-info/WHEEL
pyraisdk-0.5.6.dist-info/entry_points.txt
pyraisdk-0.5.6.dist-info/RECORD
